{"parent_group_code": "628", "parent_group_name": "Колбаса и сосиски", "products": [{"id": 9833, "name": "Продукт из мяса свинины кат. Б, грудинка сырокопченая охл.,  150 гр. нарезка", "mech": null, "img_link": "https://media.5ka.ru/media/products/4009229.jpg", "plu": 4009229, "promo": {"id": 1155586802, "date_begin": "2021-01-31", "date_end": "2021-03-02", "type": "", "description": "", "kind": "Z011", "expired_at": 12}, "current_prices": {"price_reg__min": 144.99, "price_promo__min": 89.99}, "store_name": null}, {"id": 9706, "name": "Окорок Хамон, свиной, сырокопченый, Егорьевский, 55 г", "mech": null, "img_link": "https://media.5ka.ru/media/products/3611775.jpg", "plu": 3611775, "promo": {"id": 1155586802, "date_begin": "2021-01-31", "date_end": "2021-03-02", "type": "", "description": "", "kind": "Z011", "expired_at": 12}, "current_prices": {"price_reg__min": 118.99, "price_promo__min": 99.99}, "store_name": null}, {"id": 9779, "name": "Колбаса Верона, сыровяленая, мясницкий Ряд, 90 г", "mech": null, "img_link": "https://media.5ka.ru/media/products/3684835.jpg", "plu": 3684835, "promo": {"id": 1155586802, "date_begin": "2021-01-31", "date_end": "2021-03-02", "type": "", "description": "", "kind": "Z011", "expired_at": 12}, "current_prices": {"price_reg__min": 142.99, "price_promo__min": 99.99}, "store_name": null}, {"id": 29181, "name": "Колбаса Совиньон; Салями Парма, сырокопчёная, Егорьевский МК, 100 г", "mech": null, "img_link": "https://media.5ka.ru/media/products/3460891.jpg", "plu": 3460891, "promo": {"id": 1163869036, "date_begin": "2021-02-16", "date_end": "2021-02-22", "type": "", "description": "", "kind": "Z001", "expired_at": 4}, "current_prices": {"price_reg__min": 119.0, "price_promo__min": 99.99}, "store_name": null}, {"id": 29242, "name": "Колбаса Палермо, сырокопченая, Егорьевский МК, 100 г", "mech": null, "img_link": "https://media.5ka.ru/media/products/3622973.jpg", "plu": 3622973, "promo": {"id": 1163869036, "date_begin": "2021-02-16", "date_end": "2021-02-22", "type": "", "description": "", "kind": "Z001", "expired_at": 4}, "current_prices": {"price_reg__min": 128.99, "price_promo__min": 99.99}, "store_name": null}, {"id": 29168, "name": "Бекон Велком, сырокопченый, 200 г", "mech": null, "img_link": "https://media.5ka.ru/media/products/3443644.jpg", "plu": 3443644, "promo": {"id": 1163869036, "date_begin": "2021-02-16", "date_end": "2021-02-22", "type": "", "description": "", "kind": "Z001", "expired_at": 4}, "current_prices": {"price_reg__min": 229.99, "price_promo__min": 119.99}, "store_name": null}, {"id": 29214, "name": "РЕМИТ Шейка из свинины к/в кат.Б 150г", "mech": null, "img_link": "https://media.5ka.ru/media/products/3499533.jpg", "plu": 3499533, "promo": {"id": 1163869036, "date_begin": "2021-02-16", "date_end": "2021-02-22", "type": "", "description": "", "kind": "Z001", "expired_at": 4}, "current_prices": {"price_reg__min": 129.0, "price_promo__min": 119.99}, "store_name": null}, {"id": 29351, "name": "Мясной продукт колбасное изделие варёно-копченое категории Б \"Великолукский МК\" сервелат \"Зернистый\", 400 г", "mech": null, "img_link": "https://media.5ka.ru/media/products/4012355.jpg", "plu": 4012355, "promo": {"id": 1163869036, "date_begin": "2021-02-16", "date_end": "2021-02-22", "type": "", "description": "", "kind": "Z001", "expired_at": 4}, "current_prices": {"price_reg__min": 189.99, "price_promo__min": 119.99}, "store_name": null}, {"id": 29122, "name": "Ветчина Столичная Вязанка, Стародворские колбасы, 500 г", "mech": null, "img_link": "https://media.5ka.ru/media/products/3363599.jpg", "plu": 3363599, "promo": {"id": 1163869036, "date_begin": "2021-02-16", "date_end": "2021-02-22", "type": "", "description": "", "kind": "Z001", "expired_at": 4}, "current_prices": {"price_reg__min": 193.0, "price_promo__min": 124.99}, "store_name": null}, {"id": 9870, "name": "Продукт мясной копчено-вареный из свинины Орех «Домашний» категории А 300г", "mech": null, "img_link": "https://media.5ka.ru/media/products/4048071.jpg", "plu": 4048071, "promo": {"id": 1155586802, "date_begin": "2021-01-31", "date_end": "2021-03-02", "type": "", "description": "", "kind": "Z011", "expired_at": 12}, "current_prices": {"price_reg__min": 169.99, "price_promo__min": 129.99}, "store_name": null}, {"id": 29220, "name": "Сосиски Докторские, Рублевский МК, 480 г", "mech": null, "img_link": "https://media.5ka.ru/media/products/3502098.jpg", "plu": 3502098, "promo": {"id": 1163869036, "date_begin": "2021-02-16", "date_end": "2021-02-22", "type": "", "description": "", "kind": "Z001", "expired_at": 4}, "current_prices": {"price_reg__min": 209.0, "price_promo__min": 129.99}, "store_name": null}, {"id": 9864, "name": "Изделие колбасное варёное мясосодержащее. Сосиски «Венские». 450г", "mech": null, "img_link": "https://media.5ka.ru/media/products/4045572.jpg", "plu": 4045572, "promo": {"id": 1155586802, "date_begin": "2021-01-31", "date_end": "2021-03-02", "type": "", "description": "", "kind": "Z011", "expired_at": 12}, "current_prices": {"price_reg__min": 229.99, "price_promo__min": 139.99}, "store_name": null}, {"id": 29376, "name": "МЯС.ФЕРМА Холодец из свинины и говядины 400 гр.", "mech": null, "img_link": "https://media.5ka.ru/media/products/4054599.jpg", "plu": 4054599, "promo": {"id": 1163869036, "date_begin": "2021-02-16", "date_end": "2021-02-22", "type": "", "description": "", "kind": "Z001", "expired_at": 4}, "current_prices": {"price_reg__min": 189.99, "price_promo__min": 149.99}, "store_name": null}, {"id": 9852, "name": "Мясной продукт из свинины вареный. \"Ветчина для завтрака\" категории А. 0,400 кг МИРАТОРГ", "mech": null, "img_link": "https://media.5ka.ru/media/products/4037352.jpg", "plu": 4037352, "promo": {"id": 1155586802, "date_begin": "2021-01-31", "date_end": "2021-03-02", "type": "", "description": "", "kind": "Z011", "expired_at": 12}, "current_prices": {"price_reg__min": 265.99, "price_promo__min": 169.99}, "store_name": null}, {"id": 29237, "name": "Свинина Деликатесная, Папа Может, 400 г", "mech": null, "img_link": "https://media.5ka.ru/media/products/3607295.jpg", "plu": 3607295, "promo": {"id": 1163869036, "date_begin": "2021-02-16", "date_end": "2021-02-22", "type": "", "description": "", "kind": "Z001", "expired_at": 4}, "current_prices": {"price_reg__min": 175.0, "price_promo__min": 169.99}, "store_name": null}, {"id": 29259, "name": "Мясной продукт категории Б, охлажденный. Колбаса полукопченая \"Краковская\" 1кг", "mech": null, "img_link": "https://media.5ka.ru/media/products/3631119.jpg", "plu": 3631119, "promo": {"id": 1163869036, "date_begin": "2021-02-16", "date_end": "2021-02-22", "type": "", "description": "", "kind": "Z001", "expired_at": 4}, "current_prices": {"price_reg__min": 299.99, "price_promo__min": 199.99}, "store_name": null}, {"id": 9708, "name": "Колбаса Салями Венская, сырокопченая, Клинский мк, 300 г", "mech": null, "img_link": "https://media.5ka.ru/media/products/3620876.jpg", "plu": 3620876, "promo": {"id": 1155586802, "date_begin": "2021-01-31", "date_end": "2021-03-02", "type": "", "description": "", "kind": "Z011", "expired_at": 12}, "current_prices": {"price_reg__min": 288.99, "price_promo__min": 219.99}, "store_name": null}, {"id": 9676, "name": "МДБ Шпикачки ДОМАШНИЕ 480г", "mech": null, "img_link": "https://media.5ka.ru/media/products/3472486.jpg", "plu": 3472486, "promo": {"id": 1155586802, "date_begin": "2021-01-31", "date_end": "2021-03-02", "type": "", "description": "", "kind": "Z011", "expired_at": 12}, "current_prices": {"price_reg__min": 299.0, "price_promo__min": 229.99}, "store_name": null}, {"id": 9771, "name": "МИРАТОРГ Колб.МОСКОВСКАЯ в/к кат.А 375г", "mech": null, "img_link": "https://media.5ka.ru/media/products/3683730.jpg", "plu": 3683730, "promo": {"id": 1155586802, "date_begin": "2021-01-31", "date_end": "2021-03-02", "type": "", "description": "", "kind": "Z011", "expired_at": 12}, "current_prices": {"price_reg__min": 339.99, "price_promo__min": 229.99}, "store_name": null}, {"id": 9684, "name": "Колбаса Балыковая, Ближние Горки, 490 г", "mech": null, "img_link": "https://media.5ka.ru/media/products/3490986.jpg", "plu": 3490986, "promo": {"id": 1155586802, "date_begin": "2021-01-31", "date_end": "2021-03-02", "type": "", "description": "", "kind": "Z011", "expired_at": 12}, "current_prices": {"price_reg__min": 359.99, "price_promo__min": 249.99}, "store_name": null}]}